LICENSE.txt
MANIFEST.in
README.rst
bootstrap.py
pavement.py
paver-minilib.zip
requirements.txt
setup.py
docs/changes.rst
docs/conf.py
docs/index.rst
docs/othertools.rst
docs/overview.rst
docs/standards.rst
docs/_static/.gitignore
docs/_templates/.gitignore
huTools/NetStringIO.py
huTools/ReReadingConfigParser.py
huTools/__init__.py
huTools/_decorator.py
huTools/_jsonlib.py
huTools/aggregation.py
huTools/async.py
huTools/bank.py
huTools/checksumming.py
huTools/couch.py
huTools/daemon.py
huTools/decorators.py
huTools/fmtp.py
huTools/fs.py
huTools/huLint.py
huTools/hujson.py
huTools/humessaging.py
huTools/luids.py
huTools/monetary.py
huTools/obfuscation.py
huTools/postmark.py
huTools/printing.py
huTools/protocols.py
huTools/pyjasper.py
huTools/rest.py
huTools/robusttypecasts.py
huTools/structured.py
huTools/unicode.py
huTools/world.py
huTools/xmltools.py
huTools.egg-info/PKG-INFO
huTools.egg-info/SOURCES.txt
huTools.egg-info/dependency_links.txt
huTools.egg-info/entry_points.txt
huTools.egg-info/not-zip-safe
huTools.egg-info/requires.txt
huTools.egg-info/top_level.txt
huTools/calendar/__init__.py
huTools/calendar/count_weekends.py
huTools/calendar/formats.py
huTools/calendar/tools.py
huTools/calendar/workdays.py
huTools/http/__init__.py
huTools/http/engine_appengine.py
huTools/http/engine_httplib2.py
huTools/http/poster_encode.py
huTools/http/test.py
huTools/http/tools.py
huTools/http/_httplib2/__init__.py
huTools/http/_httplib2/iri2uri.py