Metadata-Version: 1.0
Name: huTools
Version: 0.62
Summary: Various tiny tools and toys to make Python coding less work more fun.
Home-page: http://hudora.github.com/huTools/
Author: Maximillian Dornseif
Author-email: md@hudora.de
License: BSD
Keywords: python library
Platform: UNKNOWN
Classifier: Development Status :: 5 - Production/Stable
